huddle01_python/__init__.py
huddle01_python/__version__.py
huddle01_python/access_token.py
huddle01_python/active_speaker.py
huddle01_python/async_manager.py
huddle01_python/bot.py
huddle01_python/emitter.py
huddle01_python/handlers/__init__.py
huddle01_python/handlers/local_peer_handler.py
huddle01_python/handlers/remote_peer_handler.py
huddle01_python/handlers/room_handler.py
huddle01_python/handlers/socket_handler.py
huddle01_python/huddle_client.py
huddle01_python/local_peer.py
huddle01_python/log.py
huddle01_python/permissions.py
huddle01_python/proto/client/app_data_pb2.py
huddle01_python/proto/client/app_data_pb2.pyi
huddle01_python/proto/client/permissions_pb2.py
huddle01_python/proto/client/permissions_pb2.pyi
huddle01_python/proto/client/request_pb2.py
huddle01_python/proto/client/request_pb2.pyi
huddle01_python/proto/client/response_pb2.py
huddle01_python/proto/client/response_pb2.pyi
huddle01_python/proto/client/room_control_pb2.py
huddle01_python/proto/client/room_control_pb2.pyi
huddle01_python/proto/rtc/cascading_pb2.py
huddle01_python/proto/rtc/cascading_pb2.pyi
huddle01_python/proto/rtc/rtp_capabilities_pb2.py
huddle01_python/proto/rtc/rtp_capabilities_pb2.pyi
huddle01_python/proto/rtc/rtp_parameters_pb2.py
huddle01_python/proto/rtc/rtp_parameters_pb2.pyi
huddle01_python/proto/rtc/sctp_capabilities_pb2.py
huddle01_python/proto/rtc/sctp_capabilities_pb2.pyi
huddle01_python/proto/rtc/sctp_stream_parameters_pb2.py
huddle01_python/proto/rtc/sctp_stream_parameters_pb2.pyi
huddle01_python/proto/rtc/sdp_info_pb2.py
huddle01_python/proto/rtc/sdp_info_pb2.pyi
huddle01_python/remote_peer.py
huddle01_python/room.py
huddle01_python/socket.py
huddle01_python/utils.py
huddle01_python-0.1.1a2.dist-info/METADATA
huddle01_python-0.1.1a2.dist-info/WHEEL
huddle01_python-0.1.1a2.dist-info/entry_points.txt
huddle01_python-0.1.1a2.dist-info/RECORD
