Metadata-Version: 2.1
Name: huddle01-python
Version: 0.1.1a2
Summary: 
License: BSD-3-Clause
Keywords: huddle01,video,conferencing
Author: Om Gupta
Author-email: omgupta0720@gmail.com
Maintainer: Om Gupta
Maintainer-email: omgupta0720@gmail.com
Requires-Python: >=3.12.7,<4.0.0
Classifier: License :: OSI Approved :: BSD License
Classifier: Programming Language :: Python :: 3
Requires-Dist: aiohttp (>=3.10.10,<4.0.0)
Requires-Dist: asyncio (>=3.4.3,<4.0.0)
Requires-Dist: av (>=11.0.0,<12.0.0)
Requires-Dist: google-cloud-speech (>=2.28.0,<3.0.0)
Requires-Dist: google-crc32c (>=1.6.0,<2.0.0)
Requires-Dist: numpy (>=2.1.2,<3.0.0)
Requires-Dist: protobuf (>=5.28.2,<6.0.0)
Requires-Dist: pydantic (>=1.8.1,<2.0.0)
Requires-Dist: pydub (>=0.25.1,<0.26.0)
Requires-Dist: pyee (==11.1.0)
Requires-Dist: pymediasoup (>=1.0.1,<2.0.0)
Requires-Dist: python-dotenv (>=1.0.1,<2.0.0)
Requires-Dist: ruff (>=0.6.9,<0.7.0)
Requires-Dist: sounddevice (>=0.5.1,<0.6.0)
Requires-Dist: soundfile (>=0.12.1,<0.13.0)
Requires-Dist: websockets (>=13.1,<14.0)
